aosman_foo
