Metadata-Version: 1.0
Name: aosman-foo
Version: 0.2
Summary: very nice
Home-page: UNKNOWN
Author: UNKNOWN
Author-email: UNKNOWN
License: UNKNOWN
Platform: UNKNOWN
